aiai_eval/__init__.py
aiai_eval/automatic_speech_recognition.py
aiai_eval/cli.py
aiai_eval/co2.py
aiai_eval/config.py
aiai_eval/country_codes.py
aiai_eval/evaluator.py
aiai_eval/exceptions.py
aiai_eval/gui.py
aiai_eval/hf_hub.py
aiai_eval/image_to_text.py
aiai_eval/metric_configs.py
aiai_eval/named_entity_recognition.py
aiai_eval/question_answering.py
aiai_eval/scoring.py
aiai_eval/sequence_classification.py
aiai_eval/task.py
aiai_eval/task_configs.py
aiai_eval/task_factory.py
aiai_eval/utils.py
aiai_eval-0.0.1.dist-info/entry_points.txt
aiai_eval-0.0.1.dist-info/LICENSE
aiai_eval-0.0.1.dist-info/WHEEL
aiai_eval-0.0.1.dist-info/METADATA
aiai_eval-0.0.1.dist-info/RECORD
