Metadata-Version: 2.1
Name: aiai-eval
Version: 0.0.1
Summary: Evaluation of finetuned models.
License: MIT
Author: Dan Saattrup Nielsen
Author-email: dan.nielsen@alexandra.dk
Requires-Python: >=3.8,<3.11
Classifier: License :: OSI Approved :: MIT License
Classifier: Programming Language :: Python :: 3
Classifier: Programming Language :: Python :: 3.10
Classifier: Programming Language :: Python :: 3.8
Classifier: Programming Language :: Python :: 3.9
Requires-Dist: codecarbon (>=2.1.3,<3.0.0)
Requires-Dist: datasets (>=2.4.0,<3.0.0)
Requires-Dist: fsspec (>=2022.7.1,<2023.0.0)
Requires-Dist: gradio (>=3.1.7,<4.0.0)
Requires-Dist: huggingface-hub (>=0.8.1,<1.0.0)
Requires-Dist: protobuf (>=4.21.4,<5.0.0)
Requires-Dist: sentencepiece (>=0.1.96,<0.2.0)
Requires-Dist: seqeval (>=1.2.2,<2.0.0)
Requires-Dist: spacy (>=3.4.1,<4.0.0)
Requires-Dist: termcolor (>=1.1.0,<2.0.0)
Requires-Dist: torch (>=1.12.0,<2.0.0)
Requires-Dist: tqdm (>=4.64.0,<5.0.0)
Requires-Dist: transformers (>=4.21.0,<5.0.0)
